[
    {
        "img": "https://i.ibb.co/rvNRfnM/todd-kent-7-Jph-G0-K8z-Y-unsplash.jpg",
        "name": "Howell Anderson",
        "expertize": "-Alrounder Expert-"
    },
    {
        "img": "https://i.ibb.co/qyPmtqj/christian-buehner-BDd9kmf8k-Qk-unsplash.jpg",
        "name": "David Anderson",
        "expertize": "-Alrounder Expert-"
    },
    {
        "img": "https://i.ibb.co/P9hBPL3/1-4.jpg",
        "name": "Luwise Anderson",
        "expertize": "-Alrounder Expert-"
    },
    {
        "img": "https://i.ibb.co/YbMkMCF/1-1.jpg",
        "name": "Even Anderson",
        "expertize": "-Alrounder Expert-"
    }
]